mycometo/__init__.py
mycometo/connection.py
mycometo/device.py
mycometo/engine.py
mycometo/enums.py
mycometo/role.py
mycometo/core/__init__.py
mycometo/core/internal.py
mycometo-0.0.4.dist-info/LICENSE
mycometo-0.0.4.dist-info/METADATA
mycometo-0.0.4.dist-info/WHEEL
mycometo-0.0.4.dist-info/top_level.txt
mycometo-0.0.4.dist-info/RECORD
